MANIFEST.in
README.rst
VERSION
setup.py
python_build/__init__.py
python_build/__init__.pyc
python_build/build.py
python_build/build.pyc
python_build.egg-info/PKG-INFO
python_build.egg-info/SOURCES.txt
python_build.egg-info/dependency_links.txt
python_build.egg-info/entry_points.txt
python_build.egg-info/not-zip-safe
python_build.egg-info/top_level.txt
python_build/bin/python-build
python_build/share/python-build/2.1.3
python_build/share/python-build/2.2.3
python_build/share/python-build/2.3.7
python_build/share/python-build/2.4
python_build/share/python-build/2.4.1
python_build/share/python-build/2.4.2
python_build/share/python-build/2.4.3
python_build/share/python-build/2.4.4
python_build/share/python-build/2.4.5
python_build/share/python-build/2.4.6
python_build/share/python-build/2.5
python_build/share/python-build/2.5.1
python_build/share/python-build/2.5.2
python_build/share/python-build/2.5.3
python_build/share/python-build/2.5.4
python_build/share/python-build/2.5.5
python_build/share/python-build/2.5.6
python_build/share/python-build/2.6.6
python_build/share/python-build/2.6.7
python_build/share/python-build/2.6.8
python_build/share/python-build/2.6.9
python_build/share/python-build/2.7
python_build/share/python-build/2.7-dev
python_build/share/python-build/2.7.1
python_build/share/python-build/2.7.10
python_build/share/python-build/2.7.11
python_build/share/python-build/2.7.11rc1
python_build/share/python-build/2.7.2
python_build/share/python-build/2.7.3
python_build/share/python-build/2.7.4
python_build/share/python-build/2.7.5
python_build/share/python-build/2.7.6
python_build/share/python-build/2.7.7
python_build/share/python-build/2.7.8
python_build/share/python-build/2.7.9
python_build/share/python-build/3.0.1
python_build/share/python-build/3.1
python_build/share/python-build/3.1-dev
python_build/share/python-build/3.1.1
python_build/share/python-build/3.1.2
python_build/share/python-build/3.1.3
python_build/share/python-build/3.1.4
python_build/share/python-build/3.1.5
python_build/share/python-build/3.2
python_build/share/python-build/3.2-dev
python_build/share/python-build/3.2.1
python_build/share/python-build/3.2.2
python_build/share/python-build/3.2.3
